hecplus/__init__.py
hecplus/pb_class_hechms.py
hecplus/pb_class_hechms_basin.py
hecplus/pb_class_hecras.py
hecplus/pb_class_hecras_controller.py
hecplus/pb_class_hecras_flow_unsteady.py
hecplus/pb_class_hecras_geom.py
hecplus/pb_class_hecras_plan.py
hecplus/pb_class_hecras_results.py
hecplus/pb_class_hecras_review.py
hecplus/pb_functions_hec.py
hecplus/pb_functions_hec_dss.py
hecplus/pb_functions_hechms.py
hecplus/pb_functions_hecras.py
hecplus-0.3.7.dist-info/licenses/LICENSE
hecplus-0.3.7.dist-info/METADATA
hecplus-0.3.7.dist-info/WHEEL
hecplus-0.3.7.dist-info/top_level.txt
hecplus-0.3.7.dist-info/RECORD
