Metadata-Version: 2.4
Name: hecplus
Version: 0.3.7
Summary: Helper functions for working with Hydrologic Engineering Center (HEC) softwares
Author: Prashana Bajracharya
Author-email: pajracharya713@gmail.com
Keywords: hec,hecras,hechms
Classifier: Programming Language :: Python :: 3
Classifier: Programming Language :: Python :: 3.10
Classifier: Programming Language :: Python :: 3.11
Classifier: Programming Language :: Python :: 3.12
Classifier: License :: OSI Approved :: MIT License
Classifier: Development Status :: 4 - Beta
Classifier: Topic :: Scientific/Engineering :: Hydrology
Requires-Python: >=3.10
License-File: LICENSE
Requires-Dist: dsplus
Requires-Dist: pandas
Requires-Dist: h5py
Requires-Dist: hecdss
Dynamic: author
Dynamic: author-email
Dynamic: classifier
Dynamic: description
Dynamic: description-content-type
Dynamic: keywords
Dynamic: license-file
Dynamic: requires-dist
Dynamic: requires-python
Dynamic: summary
